autogen_toolsmith/__init__.py
autogen_toolsmith/cli/__init__.py
autogen_toolsmith/cli/commands.py
autogen_toolsmith/generator/__init__.py
autogen_toolsmith/generator/code_generator.py
autogen_toolsmith/generator/prompt_templates.py
autogen_toolsmith/storage/__init__.py
autogen_toolsmith/storage/registry.py
autogen_toolsmith/storage/versioning.py
autogen_toolsmith/tools/__init__.py
autogen_toolsmith/tools/base/__init__.py
autogen_toolsmith/tools/base/tool_base.py
autogen_toolsmith/tools/catalog/__init__.py
autogen_toolsmith/tools/catalog/api_tools/__init__.py
autogen_toolsmith/tools/catalog/data_tools/__init__.py
autogen_toolsmith/tools/catalog/utility_tools/__init__.py
autogen_toolsmith/tools/catalog/utility_tools/text_processor.py
autogen_toolsmith-0.1.0.dist-info/LICENSE
autogen_toolsmith-0.1.0.dist-info/METADATA
autogen_toolsmith-0.1.0.dist-info/WHEEL
autogen_toolsmith-0.1.0.dist-info/entry_points.txt
autogen_toolsmith-0.1.0.dist-info/top_level.txt
autogen_toolsmith-0.1.0.dist-info/RECORD
