Metadata-Version: 2.2
Name: autogen-toolsmith
Version: 0.1.0
Summary: AutoGen Toolsmith: Automatically generate tools for AutoGen agents
Author: AutoGen Toolsmith Team
License: MIT
Project-URL: Homepage, https://github.com/yourusername/autogen-toolsmith
Project-URL: Bug Tracker, https://github.com/yourusername/autogen-toolsmith/issues
Classifier: Programming Language :: Python :: 3
Classifier: License :: OSI Approved :: MIT License
Classifier: Operating System :: OS Independent
Requires-Python: >=3.8
License-File: LICENSE
Requires-Dist: autogen-agentchat>=0.4.0
Requires-Dist: autogen-core>=0.4.0
Requires-Dist: autogen-ext>=0.4.0
Requires-Dist: openai>=1.0.0
Requires-Dist: pytest>=7.0.0
Provides-Extra: dev
Requires-Dist: black; extra == "dev"
Requires-Dist: isort; extra == "dev"
Requires-Dist: mypy; extra == "dev"
Requires-Dist: flake8; extra == "dev"
Requires-Dist: pytest; extra == "dev"
Requires-Dist: pytest-cov; extra == "dev"
